TimeLineCluster/ConfigReader.py
TimeLineCluster/DBConnector.py
TimeLineCluster/GenericController.py
TimeLineCluster/LogController.py
TimeLineCluster/UtilsController.py
TimeLineCluster/__init__.py
TimeLineCluster/utils/js/getWOY.js
timelinecluster-3.1.dist-info/METADATA
timelinecluster-3.1.dist-info/WHEEL
timelinecluster-3.1.dist-info/top_level.txt
timelinecluster-3.1.dist-info/RECORD
