Metadata-Version: 2.1
Name: timelinecluster
Version: 3.1
Summary: This is timelinecluster.
Home-page: UNKNOWN
Author: author test
Author-email: 
License: MIT
Platform: UNKNOWN
Requires-Python: >=3.6
